hypertic/__init__.py
hypertic/agents/__init__.py
hypertic/agents/agent.py
hypertic/embedders/__init__.py
hypertic/embedders/base.py
hypertic/embedders/cohere/__init__.py
hypertic/embedders/cohere/cohere.py
hypertic/embedders/google/__init__.py
hypertic/embedders/google/google.py
hypertic/embedders/huggingface/__init__.py
hypertic/embedders/huggingface/huggingface.py
hypertic/embedders/mistral/__init__.py
hypertic/embedders/mistral/mistral.py
hypertic/embedders/openai/__init__.py
hypertic/embedders/openai/openai.py
hypertic/embedders/sentencetransformer/__init__.py
hypertic/embedders/sentencetransformer/sentencetransformer.py
hypertic/guardrails/__init__.py
hypertic/guardrails/base.py
hypertic/guardrails/guardrails.py
hypertic/memory/__init__.py
hypertic/memory/base.py
hypertic/memory/inmemory.py
hypertic/memory/mongodb/__init__.py
hypertic/memory/mongodb/mongo.py
hypertic/memory/mongodb/mongo_async.py
hypertic/memory/postgres/__init__.py
hypertic/memory/postgres/postgres.py
hypertic/memory/postgres/postgres_async.py
hypertic/memory/redis/__init__.py
hypertic/memory/redis/async_cache.py
hypertic/memory/redis/cache.py
hypertic/models/__init__.py
hypertic/models/base.py
hypertic/models/events.py
hypertic/models/metrics.py
hypertic/models/anthropic/__init__.py
hypertic/models/anthropic/anthropic.py
hypertic/models/cohere/__init__.py
hypertic/models/cohere/cohere.py
hypertic/models/deepseek/__init__.py
hypertic/models/deepseek/deepseek.py
hypertic/models/fireworks/__init__.py
hypertic/models/fireworks/fireworks.py
hypertic/models/google/__init__.py
hypertic/models/google/google.py
hypertic/models/groq/__init__.py
hypertic/models/groq/groq.py
hypertic/models/mistral/__init__.py
hypertic/models/mistral/mistral.py
hypertic/models/moonshot/__init__.py
hypertic/models/moonshot/moonshot.py
hypertic/models/openai/__init__.py
hypertic/models/openai/openaichat.py
hypertic/models/openai/openairesponse.py
hypertic/models/openrouter/__init__.py
hypertic-0.0.2.dist-info/METADATA
hypertic-0.0.2.dist-info/WHEEL
hypertic-0.0.2.dist-info/licenses/LICENSE
hypertic-0.0.2.dist-info/RECORD
