Metadata-Version: 2.4
Name: hypertic
Version: 0.0.2
Summary: The fastest and easiest way to build AI agent applications
Project-URL: Homepage, https://github.com/hypertic-ai/hypertic
Project-URL: Repository, https://github.com/hypertic-ai/hypertic
Author-email: prasad mahamulkar <prsd.mahamulkar@gmail.com>
License: Apache-2.0
License-File: LICENSE
Classifier: Intended Audience :: Developers
Classifier: License :: OSI Approved :: Apache Software License
Classifier: Operating System :: OS Independent
Classifier: Programming Language :: Python :: 3
Classifier: Programming Language :: Python :: 3.10
Classifier: Programming Language :: Python :: 3.11
Classifier: Programming Language :: Python :: 3.12
Classifier: Programming Language :: Python :: 3.13
Classifier: Topic :: Software Development :: Libraries :: Python Modules
Requires-Python: >=3.10
Requires-Dist: aiohttp
Requires-Dist: beautifulsoup4
Requires-Dist: mcp>=1.0.0
Requires-Dist: pydantic>=2.0.0
Requires-Dist: pypdf2
Requires-Dist: python-docx
Requires-Dist: pyyaml
Requires-Dist: requests
Requires-Dist: striprtf
Provides-Extra: all
Requires-Dist: anthropic; extra == 'all'
Requires-Dist: asyncpg; extra == 'all'
Requires-Dist: chromadb; extra == 'all'
Requires-Dist: cohere; extra == 'all'
Requires-Dist: google-genai; extra == 'all'
Requires-Dist: greenlet; extra == 'all'
Requires-Dist: groq; extra == 'all'
Requires-Dist: huggingface-hub; extra == 'all'
Requires-Dist: mistralai; extra == 'all'
Requires-Dist: motor; extra == 'all'
Requires-Dist: openai; extra == 'all'
Requires-Dist: pgvector; extra == 'all'
Requires-Dist: pinecone; extra == 'all'
Requires-Dist: psycopg2-binary; extra == 'all'
Requires-Dist: pymongo; extra == 'all'
Requires-Dist: qdrant-client; extra == 'all'
Requires-Dist: redis; extra == 'all'
Requires-Dist: sentence-transformers; extra == 'all'
Requires-Dist: sqlalchemy; extra == 'all'
Provides-Extra: anthropic
Requires-Dist: anthropic; extra == 'anthropic'
Provides-Extra: chromadb
Requires-Dist: chromadb; extra == 'chromadb'
Provides-Extra: cohere
Requires-Dist: cohere; extra == 'cohere'
Provides-Extra: ddgs
Requires-Dist: ddgs; extra == 'ddgs'
Provides-Extra: embedders
Requires-Dist: cohere; extra == 'embedders'
Requires-Dist: google-genai; extra == 'embedders'
Requires-Dist: huggingface-hub; extra == 'embedders'
Requires-Dist: mistralai; extra == 'embedders'
Requires-Dist: openai; extra == 'embedders'
Requires-Dist: sentence-transformers; extra == 'embedders'
Provides-Extra: google
Requires-Dist: google-genai; extra == 'google'
Provides-Extra: groq
Requires-Dist: groq; extra == 'groq'
Provides-Extra: memory
Requires-Dist: asyncpg; extra == 'memory'
Requires-Dist: greenlet; extra == 'memory'
Requires-Dist: motor; extra == 'memory'
Requires-Dist: pgvector; extra == 'memory'
Requires-Dist: psycopg2-binary; extra == 'memory'
Requires-Dist: pymongo; extra == 'memory'
Requires-Dist: redis; extra == 'memory'
Requires-Dist: sqlalchemy; extra == 'memory'
Provides-Extra: mistral
Requires-Dist: mistralai; extra == 'mistral'
Provides-Extra: models
Requires-Dist: anthropic; extra == 'models'
Requires-Dist: cohere; extra == 'models'
Requires-Dist: google-genai; extra == 'models'
Requires-Dist: groq; extra == 'models'
Requires-Dist: mistralai; extra == 'models'
Requires-Dist: openai; extra == 'models'
Provides-Extra: mongodb
Requires-Dist: motor; extra == 'mongodb'
Requires-Dist: pymongo; extra == 'mongodb'
Provides-Extra: openai
Requires-Dist: openai; extra == 'openai'
Provides-Extra: pgvector
Requires-Dist: asyncpg; extra == 'pgvector'
Requires-Dist: pgvector; extra == 'pgvector'
Requires-Dist: psycopg2-binary; extra == 'pgvector'
Requires-Dist: sqlalchemy; extra == 'pgvector'
Provides-Extra: pinecone
Requires-Dist: pinecone; extra == 'pinecone'
Provides-Extra: postgres
Requires-Dist: asyncpg; extra == 'postgres'
Requires-Dist: greenlet; extra == 'postgres'
Requires-Dist: pgvector; extra == 'postgres'
Requires-Dist: psycopg2-binary; extra == 'postgres'
Requires-Dist: sqlalchemy; extra == 'postgres'
Provides-Extra: qdrant
Requires-Dist: qdrant-client; extra == 'qdrant'
Provides-Extra: redis
Requires-Dist: redis; extra == 'redis'
Provides-Extra: vectordb
Requires-Dist: asyncpg; extra == 'vectordb'
Requires-Dist: chromadb; extra == 'vectordb'
Requires-Dist: motor; extra == 'vectordb'
Requires-Dist: pgvector; extra == 'vectordb'
Requires-Dist: pinecone; extra == 'vectordb'
Requires-Dist: psycopg2-binary; extra == 'vectordb'
Requires-Dist: pymongo; extra == 'vectordb'
Requires-Dist: qdrant-client; extra == 'vectordb'
Requires-Dist: sqlalchemy; extra == 'vectordb'
